ni/protobuf/types/__init__.py
ni/protobuf/types/array_pb2.py
ni/protobuf/types/array_pb2.pyi
ni/protobuf/types/attribute_value_pb2.py
ni/protobuf/types/attribute_value_pb2.pyi
ni/protobuf/types/extended_property_conversion.py
ni/protobuf/types/precision_duration_conversion.py
ni/protobuf/types/precision_duration_pb2.py
ni/protobuf/types/precision_duration_pb2.pyi
ni/protobuf/types/precision_timestamp_conversion.py
ni/protobuf/types/precision_timestamp_pb2.py
ni/protobuf/types/precision_timestamp_pb2.pyi
ni/protobuf/types/py.typed
ni/protobuf/types/scalar_conversion.py
ni/protobuf/types/scalar_pb2.py
ni/protobuf/types/scalar_pb2.pyi
ni/protobuf/types/vector_conversion.py
ni/protobuf/types/vector_pb2.py
ni/protobuf/types/vector_pb2.pyi
ni/protobuf/types/waveform_conversion.py
ni/protobuf/types/waveform_pb2.py
ni/protobuf/types/waveform_pb2.pyi
ni/protobuf/types/waveform_wrappers_pb2.py
ni/protobuf/types/waveform_wrappers_pb2.pyi
ni/protobuf/types/xydata_conversion.py
ni/protobuf/types/xydata_pb2.py
ni/protobuf/types/xydata_pb2.pyi
ni_protobuf_types-1.1.0.dist-info/METADATA
ni_protobuf_types-1.1.0.dist-info/WHEEL
ni_protobuf_types-1.1.0.dist-info/RECORD
