Metadata-Version: 2.3
Name: ni.protobuf.types
Version: 1.1.0
Summary: Protobuf data types for NI gRPC APIs
License: MIT
Keywords: ni-apis,protobuf
Author: NI
Author-email: opensource@ni.com
Maintainer: Joe Friedrichsen
Maintainer-email: joe.friedrichsen@emerson.com
Requires-Python: >=3.10,<4.0
Classifier: Development Status :: 5 - Production/Stable
Classifier: Intended Audience :: Developers
Classifier: Intended Audience :: Manufacturing
Classifier: Intended Audience :: Science/Research
Classifier: License :: OSI Approved :: MIT License
Classifier: Operating System :: Microsoft :: Windows
Classifier: Operating System :: POSIX
Classifier: Programming Language :: Python :: 3
Classifier: Programming Language :: Python :: 3.10
Classifier: Programming Language :: Python :: 3.11
Classifier: Programming Language :: Python :: 3.12
Classifier: Programming Language :: Python :: 3.13
Classifier: Programming Language :: Python :: 3.14
Classifier: Programming Language :: Python :: Implementation :: CPython
Requires-Dist: nitypes (>=1.1.0dev1)
Requires-Dist: protobuf (>=4.21)
Project-URL: Documentation, https://niprotobuftypes.readthedocs.io/en/latest/
Project-URL: Repository, https://github.com/ni/ni-apis-python
